differintegral_sage/__init__.py
differintegral_sage/differintegral.py
differintegral_sage-1.0.1.dist-info/LICENSE
differintegral_sage-1.0.1.dist-info/METADATA
differintegral_sage-1.0.1.dist-info/WHEEL
differintegral_sage-1.0.1.dist-info/top_level.txt
differintegral_sage-1.0.1.dist-info/RECORD
