Metadata-Version: 2.1
Name: differintegral-sage
Version: 1.0.1
Summary: SageMath Implementation of Riemann–Liouville DifferIntegral Operator
Home-page: https://github.com/mcintireevan/differintegral-sage
Author: Evan McIntire
Author-email: mcintire.evan@gmail.com
License: UNKNOWN
Platform: UNKNOWN
Classifier: Programming Language :: Python :: 3
Classifier: License :: OSI Approved :: MIT License
Classifier: Operating System :: OS Independent
Classifier: Topic :: Scientific/Engineering :: Mathematics
Requires-Python: >=3.6
